cfn_mod-0.15.16.dist-info/DESCRIPTION.rst
cfn_mod-0.15.16.dist-info/METADATA
cfn_mod-0.15.16.dist-info/RECORD
cfn_mod-0.15.16.dist-info/WHEEL
cfn_mod-0.15.16.dist-info/entry_points.txt
cfn_mod-0.15.16.dist-info/metadata.json
cfn_mod-0.15.16.dist-info/top_level.txt
cfnmod/__init__.py
cfnmod/__main__.py
cfnmod/cfnmod.py
