Metadata-Version: 2.0
Name: cfn-mod
Version: 0.15.16
Summary: CloudFormation Modules Helper
Home-page: https://github.com/PresidioManagedCloudServices/cfn-mod
Author: Jeremy Axmacher
Author-email: jaxmacher@presidio.com
License: MIT
Platform: UNKNOWN
Requires-Dist: boto3 (==1.14.38)
Requires-Dist: botocore (==1.17.38)
Requires-Dist: click (==7.1.2)
Requires-Dist: docutils (==0.15.2)
Requires-Dist: jmespath (==0.10.0)
Requires-Dist: python-dateutil (==2.8.1)
Requires-Dist: pyyaml (==5.3.1)
Requires-Dist: ruamel.yaml.clib (==0.2.0)
Requires-Dist: ruamel.yaml (==0.16.10)
Requires-Dist: s3transfer (==0.3.3)
Requires-Dist: six (==1.15.0)
Requires-Dist: urllib3 (==1.25.10)
